bdaservicetemplate/__init__.py
bdaservicetemplate/generic_service.py
bdaservicetemplate/io.py
bdaservicetemplate/pandas_service.py
bdaservicetemplate/processor_service.py
bdaservicetemplate/sink_service.py
bdaservicetemplate/source_service.py
bdaservicetemplate/spark_service.py
bdaservicetemplate/streaming_service.py
bdaservicetemplate/utils.py
bda_service_template-0.0.59.dist-info/METADATA
bda_service_template-0.0.59.dist-info/WHEEL
bda_service_template-0.0.59.dist-info/top_level.txt
bda_service_template-0.0.59.dist-info/RECORD
